loick_multiply/__init__.py
loick_multiply/multiply.py
medium_multiply/__init__.py
medium_multiply/multiplication.py
loick_multiply-0.1.0.dist-info/METADATA
loick_multiply-0.1.0.dist-info/WHEEL
loick_multiply-0.1.0.dist-info/top_level.txt
loick_multiply-0.1.0.dist-info/RECORD
