Metadata-Version: 2.1
Name: loick-multiply
Version: 0.1.0
Summary: Demo library
Home-page: https://loick-multiply.readthedocs.io/
Author: Loick Lepine
Author-email: loick.lepine@mail.mcgill.ca
License: MIT
Classifier: Intended Audience :: Developers
Classifier: License :: OSI Approved :: MIT License
Classifier: Programming Language :: Python
Classifier: Programming Language :: Python :: 3
Classifier: Programming Language :: Python :: 3.9
Classifier: Operating System :: OS Independent
Requires-Dist: numpy
